code_comments/__init__.py
code_comments/cmd.py
code_comments-0.4.0.dist-info/LICENSE
code_comments-0.4.0.dist-info/METADATA
code_comments-0.4.0.dist-info/WHEEL
code_comments-0.4.0.dist-info/entry_points.txt
code_comments-0.4.0.dist-info/RECORD
